walt/__init__.py
walt/vpn/__init__.py
walt/vpn/authtool.py
walt/vpn/client.py
walt/vpn/const.py
walt/vpn/endpoint.py
walt/vpn/server.py
walt/vpn/ssh.py
walt/vpn/tools.py
walt/vpn/ext/__init__.py
walt/vpn/ext/_loops.abi3.so
walt/vpn/ext/build.py
walt/vpn/ext/loops.c
walt/vpn/setup/S51waltvpnclient
walt/vpn/setup/__init__.py
walt/vpn/setup/user.py
walt/vpn/setup/walt-vpn-server.service
walt/vpn/setup/walt-vpn-server.socket
walt_vpn-9.0.dist-info/METADATA
walt_vpn-9.0.dist-info/WHEEL
walt_vpn-9.0.dist-info/entry_points.txt
walt_vpn-9.0.dist-info/top_level.txt
walt_vpn-9.0.dist-info/RECORD
