Metadata-Version: 2.1
Name: walt-vpn
Version: 9.0
Summary: WalT VPN components.
Home-page: https://walt-project.liglab.fr
Author: WalT developers
Author-email: walt-contact@univ-grenoble-alpes.fr
License: 3-Clause BSD
Keywords: WalT testbed
Requires-Dist: walt-common ==9.0
Requires-Dist: python-daemon <3
Requires-Dist: cffi >=1.0.0
